health_report/__init__.py
health_report/asgi.py
health_report/settings.py
health_report/urls.py
health_report/views.py
health_report/wsgi.py
demo_health_report-0.1.0.dist-info/METADATA
demo_health_report-0.1.0.dist-info/WHEEL
demo_health_report-0.1.0.dist-info/entry_points.txt
demo_health_report-0.1.0.dist-info/RECORD
