Metadata-Version: 2.3
Name: demo-health-report
Version: 0.1.0
Summary: demo
License: MIT
Author: Amrutha
Author-email: amamrutha04@gmail.com
Requires-Python: >=3.8,<4.0
Classifier: License :: OSI Approved :: MIT License
Classifier: Programming Language :: Python :: 3
Classifier: Programming Language :: Python :: 3.8
Classifier: Programming Language :: Python :: 3.9
Classifier: Programming Language :: Python :: 3.10
Classifier: Programming Language :: Python :: 3.11
Classifier: Programming Language :: Python :: 3.12
Classifier: Programming Language :: Python :: 3.13
Requires-Dist: django (>=4.0,<5.0)
Requires-Dist: djangorestframework (>=3.14,<4.0)
